aliyun_rocketmq_provider/__init__.py
aliyun_rocketmq_provider/hooks/__init__.py
aliyun_rocketmq_provider/hooks/aliyun_rocketmq.py
airflow_providers_aliyun_rocketmq-0.1.3.dist-info/LICENSE
airflow_providers_aliyun_rocketmq-0.1.3.dist-info/METADATA
airflow_providers_aliyun_rocketmq-0.1.3.dist-info/WHEEL
airflow_providers_aliyun_rocketmq-0.1.3.dist-info/entry_points.txt
airflow_providers_aliyun_rocketmq-0.1.3.dist-info/top_level.txt
airflow_providers_aliyun_rocketmq-0.1.3.dist-info/RECORD
