Metadata-Version: 2.1
Name: airflow-providers-aliyun-rocketmq
Version: 0.1.3
Summary: Airflow x Aliyun RocketMQ
Home-page: https://github.com/Ed-XCF/airflow-providers-aliyun-rocketmq
Author: Ed__xu__Ed
Author-email: m.tofu@qq.com
License: Apache License 2.0
Platform: UNKNOWN
Requires-Python: >=3.6
Requires-Dist: apache-airflow (>=2.0)
Requires-Dist: mq-http-sdk (>=1.0.3)
